openrouter_free/__init__.py
openrouter_free/client.py
openrouter_free/exceptions.py
openrouter_free/key_state.py
openrouter_free/models.py
openrouter_free/adapters/__init__.py
openrouter_free/adapters/langchain_adapter.py
openrouter_free/adapters/llama_adapter.py
openrouter_free-0.1.4.dist-info/licenses/LICENSE
openrouter_free-0.1.4.dist-info/METADATA
openrouter_free-0.1.4.dist-info/WHEEL
openrouter_free-0.1.4.dist-info/top_level.txt
openrouter_free-0.1.4.dist-info/RECORD
