Metadata-Version: 2.4
Name: openrouter-free
Version: 0.1.4
Summary: A Python client for managing multiple free OpenRouter API keys with automatic rotation
Author-email: Mediano4e <mediano4e@gmail.com>
License-Expression: MIT
Project-URL: Homepage, https://github.com/Mediano4e/openrouter-free-client
Project-URL: Repository, https://github.com/Mediano4e/openrouter-free-client
Project-URL: Issues, https://github.com/Mediano4e/openrouter-free-client/issues
Project-URL: Documentation, https://github.com/Mediano4e/openrouter-free-client#readme
Keywords: openrouter,llm,ai,llama-index,langchain,api,client
Classifier: Development Status :: 4 - Beta
Classifier: Intended Audience :: Developers
Classifier: Operating System :: OS Independent
Classifier: Programming Language :: Python :: 3
Classifier: Programming Language :: Python :: 3.8
Classifier: Programming Language :: Python :: 3.9
Classifier: Programming Language :: Python :: 3.10
Classifier: Programming Language :: Python :: 3.11
Classifier: Programming Language :: Python :: 3.12
Classifier: Topic :: Software Development :: Libraries :: Python Modules
Classifier: Topic :: Scientific/Engineering :: Artificial Intelligence
Requires-Python: >=3.8
License-File: LICENSE
Requires-Dist: openai>=1.0.0
Requires-Dist: httpx>=0.24.0
Requires-Dist: loguru>=0.7.0
Provides-Extra: llama-index
Requires-Dist: llama-index-core>=0.10.0; extra == "llama-index"
Provides-Extra: langchain
Requires-Dist: langchain-core>=0.1.0; extra == "langchain"
Provides-Extra: all
Requires-Dist: llama-index-core>=0.10.0; extra == "all"
Requires-Dist: langchain-core>=0.1.0; extra == "all"
Dynamic: license-file
